ftm_assets/__init__.py
ftm_assets/api.py
ftm_assets/cli.py
ftm_assets/logging.py
ftm_assets/logic.py
ftm_assets/model.py
ftm_assets/resolvers/__init__.py
ftm_assets/resolvers/wikidata.py
ftm_assets/settings.py
ftm_assets/store.py
ftm_assets/tasks.py
ftm_assets-0.0.4.dist-info/LICENSE
ftm_assets-0.0.4.dist-info/METADATA
ftm_assets-0.0.4.dist-info/NOTICE
ftm_assets-0.0.4.dist-info/WHEEL
ftm_assets-0.0.4.dist-info/entry_points.txt
ftm_assets-0.0.4.dist-info/RECORD
