Metadata-Version: 2.3
Name: ftm-assets
Version: 0.0.4
Summary: Assets (image) resolver for FollowTheMoney data
License: AGPLv3+
Author: Simon Wörpel
Author-email: simon.woerpel@pm.me
Requires-Python: >=3.11,<4
Classifier: Intended Audience :: Developers
Classifier: Operating System :: OS Independent
Classifier: Programming Language :: Python
Classifier: Programming Language :: Python :: 3.11
Classifier: Programming Language :: Python :: 3.12
Classifier: Programming Language :: Python :: 3.13
Provides-Extra: openaleph
Requires-Dist: anystore (>=0.3.4,<0.4.0)
Requires-Dist: fastapi (>=0.115.12,<0.116.0)
Requires-Dist: ftmq (>=0.8.4,<0.9.0)
Requires-Dist: httpx (>=0.28.1,<0.29.0)
Requires-Dist: openaleph-procrastinate (>=0.0.1,<0.0.2) ; extra == "openaleph"
Requires-Dist: pillow (>=11.2.1,<12.0.0)
Project-URL: Documentation, https://github.com/dataresearchcenter/ftm-assets
Project-URL: Homepage, https://github.com/dataresearchcenter/ftm-assets
Project-URL: Issues, https://github.com/dataresearchcenter/ftm-assets/issues
Project-URL: Repository, https://github.com/dataresearchcenter/ftm-assets
